{
  "author": "bobsingor",
  "links": [
    {
      "type": "github_repo",
      "avatarUrl": "https://avatars.githubusercontent.com/u/195636730?v=4&s=50",
      "contributors": 7,
      "description": "A PDF viewer that seamlessly integrates with any JavaScript project",
      "discussions": 17,
      "forks": 151,
      "issues": 86,
      "languages": [
        "TypeScript",
        "MDX",
        "JavaScript",
        "Vue",
        "Svelte",
        "HTML",
        "CSS",
        "Shell",
        "Dockerfile",
        "C++"
      ],
      "name": "embed-pdf-viewer",
      "owner": "embedpdf",
      "prs": 5,
      "stars": 2627,
      "url": "https://github.com/embedpdf/embed-pdf-viewer"
    }
  ]
}